LICENSE
MANIFEST.in
README.md
requirements.txt
setup.cfg
setup.py
debian/changelog
debian/compat
debian/control
debian/copyright
debian/rules
debian/source/format
origin/README.txt
origin/enum-0.4.4/LICENSE.GPL
origin/enum-0.4.4/LICENSE.PSF
origin/enum-0.4.4/MANIFEST.in
origin/enum-0.4.4/PKG-INFO
origin/enum-0.4.4/enum.py
origin/enum-0.4.4/setup.cfg
origin/enum-0.4.4/setup.py
origin/enum-0.4.4/enum.egg-info/PKG-INFO
origin/enum-0.4.4/enum.egg-info/SOURCES.txt
origin/enum-0.4.4/enum.egg-info/dependency_links.txt
origin/enum-0.4.4/enum.egg-info/not-zip-safe
origin/enum-0.4.4/enum.egg-info/requires.txt
origin/enum-0.4.4/enum.egg-info/top_level.txt
origin/enum-0.4.4/test/__init__.py
origin/enum-0.4.4/test/test_enum.py
origin/enum-0.4.4/test/tools.py
origin/smpp.pdu/.gitignore
origin/smpp.pdu/.travis.yml
origin/smpp.pdu/LICENSE
origin/smpp.pdu/MANIFEST.in
origin/smpp.pdu/README.markdown
origin/smpp.pdu/requirements.txt
origin/smpp.pdu/setup.py
origin/smpp.pdu/smpp/__init__.py
origin/smpp.pdu/smpp/pdu/__init__.py
origin/smpp.pdu/smpp/pdu/constants.py
origin/smpp.pdu/smpp/pdu/encoding.py
origin/smpp.pdu/smpp/pdu/error.py
origin/smpp.pdu/smpp/pdu/gsm_constants.py
origin/smpp.pdu/smpp/pdu/gsm_encoding.py
origin/smpp.pdu/smpp/pdu/gsm_types.py
origin/smpp.pdu/smpp/pdu/namedtuple.py
origin/smpp.pdu/smpp/pdu/operations.py
origin/smpp.pdu/smpp/pdu/pdu_encoding.py
origin/smpp.pdu/smpp/pdu/pdu_types.py
origin/smpp.pdu/smpp/pdu/sm_encoding.py
origin/smpp.pdu/smpp/pdu/smpp_time.py
origin/smpp.pdu/smpp/pdu/tests/__init__.py
origin/smpp.pdu/smpp/pdu/tests/test_gsm_encoding.py
origin/smpp.pdu/smpp/pdu/tests/test_pdu_encoding.py
origin/smpp.pdu/smpp/pdu/tests/test_pdu_types.py
origin/smpp.pdu/smpp/pdu/tests/test_sm_encoding.py
origin/smpp.pdu/smpp/pdu/tests/test_smpp_time.py
origin/smpp.twisted/.gitignore
origin/smpp.twisted/.travis.yml
origin/smpp.twisted/LICENSE
origin/smpp.twisted/MANIFEST.in
origin/smpp.twisted/README.markdown
origin/smpp.twisted/dev_requirements.txt
origin/smpp.twisted/requirements.txt
origin/smpp.twisted/setup.py
origin/smpp.twisted/smpp/__init__.py
origin/smpp.twisted/smpp/twisted/__init__.py
origin/smpp.twisted/smpp/twisted/client.py
origin/smpp.twisted/smpp/twisted/config.py
origin/smpp.twisted/smpp/twisted/protocol.py
ptsmpp.egg-info/PKG-INFO
ptsmpp.egg-info/SOURCES.txt
ptsmpp.egg-info/dependency_links.txt
ptsmpp.egg-info/not-zip-safe
ptsmpp.egg-info/requires.txt
ptsmpp.egg-info/top_level.txt
