Metadata-Version: 1.1
Name: ptsmpp
Version: 0.1.0
Summary: PTSMPP - Python Twisted SMPP 3.4 client library
Home-page: https://github.com/xanderdin/ptsmpp
Author: Alexander Pravdin
Author-email: aledin@mail.ru
License: Apache License 2.0
Keywords: ptsmpp smpp twisted
Platform: UNKNOWN
Classifier: Development Status :: 4 - Beta
Classifier: Framework :: Twisted
Classifier: Topic :: System :: Networking
Classifier: Operating System :: OS Independent
Classifier: License :: OSI Approved :: Apache Software License
Classifier: Intended Audience :: Developers
Classifier: Programming Language :: Python
Classifier: Topic :: Software Development :: Libraries :: Python Modules
